duckbin/__init__.py
duckbin-1.0.1.dist-info/LICENSE
duckbin-1.0.1.dist-info/METADATA
duckbin-1.0.1.dist-info/WHEEL
duckbin-1.0.1.dist-info/top_level.txt
duckbin-1.0.1.dist-info/RECORD
