Metadata-Version: 2.1
Name: duckbin
Version: 1.0.1
Summary: This package allows you to save any text for free on our servers. Whether it's a note, an article, or any other type of content, you can easily store it without any cost.
Home-page: https://github.com/freeutka/DuckBin
Author: freeutka
Author-email: freeutka@inbox.lv
Classifier: Programming Language :: Python :: 3
Classifier: License :: OSI Approved :: MIT License
Classifier: Operating System :: OS Independent
Requires-Python: >=3.6
License-File: LICENSE
Requires-Dist: requests
